{
  "todoList": [
    {
      "text": "asdfa",
      "isDone": false,
      "id": 1
    },
    {
      "text": "asdfds",
      "isDone": true,
      "id": 6
    },
    {
      "text": "hook",
      "isDone": false,
      "id": 10
    },
    {
      "text": "ggvg",
      "isDone": false,
      "id": 11
    },
    {
      "text": "hfe",
      "isDone": false,
      "id": 12
    },
    {
      "text": "jhfu",
      "isDone": false,
      "id": 13
    },
    {
      "text": "jwf",
      "isDone": false,
      "id": 14
    },
    {
      "text": "hh",
      "isDone": false,
      "id": 15
    },
    {
      "text": "hg",
      "isDone": false,
      "id": 16
    },
    {
      "text": "jbj",
      "isDone": false,
      "id": 17
    }
  ]
}